realm/__init__.py
realm/client.py
realm/langchain.py
realm/types.py
realm_sdk-0.1.2.dist-info/licenses/LICENSE
realm_sdk-0.1.2.dist-info/METADATA
realm_sdk-0.1.2.dist-info/WHEEL
realm_sdk-0.1.2.dist-info/top_level.txt
realm_sdk-0.1.2.dist-info/RECORD
