Metadata-Version: 2.4
Name: realm-sdk
Version: 0.1.2
Summary: Realm SDK - Observability and time-travel debugging for AI agents
Author-email: Realm Team <support@realm.space>
License: MIT
Project-URL: Homepage, https://realm.space
Project-URL: Documentation, https://docs.realm.space
Project-URL: Repository, https://github.com/neelshar/Realm
Project-URL: Bug Tracker, https://github.com/neelshar/Realm/issues
Keywords: ai,agents,observability,debugging,langchain,llm
Classifier: Development Status :: 3 - Alpha
Classifier: Intended Audience :: Developers
Classifier: License :: OSI Approved :: MIT License
Classifier: Programming Language :: Python :: 3
Classifier: Programming Language :: Python :: 3.8
Classifier: Programming Language :: Python :: 3.9
Classifier: Programming Language :: Python :: 3.10
Classifier: Programming Language :: Python :: 3.11
Classifier: Programming Language :: Python :: 3.12
Classifier: Topic :: Software Development :: Libraries :: Python Modules
Classifier: Topic :: Scientific/Engineering :: Artificial Intelligence
Requires-Python: >=3.8
License-File: LICENSE
Requires-Dist: requests>=2.31.0
Provides-Extra: langchain
Requires-Dist: langchain>=0.1.0; extra == "langchain"
Provides-Extra: dev
Requires-Dist: pytest>=7.4.0; extra == "dev"
Requires-Dist: black>=23.0.0; extra == "dev"
Requires-Dist: mypy>=1.5.0; extra == "dev"
Requires-Dist: ruff>=0.1.0; extra == "dev"
Provides-Extra: all
Requires-Dist: langchain>=0.1.0; extra == "all"
Dynamic: license-file
